MedicalAutomationService/__init__.py
MedicalAutomationService/__main__.py
MedicalAutomationService/const.py
MedicalAutomationService/service.py
pih_med_auto-1.13.dist-info/METADATA
pih_med_auto-1.13.dist-info/WHEEL
pih_med_auto-1.13.dist-info/entry_points.txt
pih_med_auto-1.13.dist-info/top_level.txt
pih_med_auto-1.13.dist-info/RECORD
