Metadata-Version: 2.1
Name: pih-med-auto
Version: 1.13
Summary: PIH Medical Automation service package
Home-page: https://pacifichosp.com/
Author: Nikita Karachentsev
Author-email: it@pacifichosp.com
License: MIT
Requires-Dist: ipih
Requires-Dist: pih-mio
